Korpora/__init__.py
Korpora/about.py
Korpora/cli.py
Korpora/korpora.py
Korpora/korpus_aihub_translation.py
Korpora/korpus_chatbot_data.py
Korpora/korpus_custom.py
Korpora/korpus_kcbert.py
Korpora/korpus_korean_hate_speech.py
Korpora/korpus_korean_parallel.py
Korpora/korpus_korean_petitions.py
Korpora/korpus_kornli.py
Korpora/korpus_korsts.py
Korpora/korpus_kowiki.py
Korpora/korpus_modu_messenger.py
Korpora/korpus_modu_morpheme.py
Korpora/korpus_modu_ne.py
Korpora/korpus_modu_news.py
Korpora/korpus_modu_spoken.py
Korpora/korpus_modu_web.py
Korpora/korpus_modu_written.py
Korpora/korpus_namuwiki.py
Korpora/korpus_naverchangwon_ner.py
Korpora/korpus_nsmc.py
Korpora/korpus_open_subtitles.py
Korpora/korpus_question_pair.py
Korpora/loader.py
Korpora/task_fetch.py
Korpora/task_lmdata.py
Korpora/utils.py
Korpora-0.2.0.dist-info/LICENSE
Korpora-0.2.0.dist-info/METADATA
Korpora-0.2.0.dist-info/WHEEL
Korpora-0.2.0.dist-info/entry_points.txt
Korpora-0.2.0.dist-info/top_level.txt
Korpora-0.2.0.dist-info/RECORD
