Metadata-Version: 2.1
Name: Korpora
Version: 0.2.0
Summary: This package provides easy-download and easy-usage for various Korean corpora.
Home-page: https://github.com/ko-nlp/Korpora
Author: ko-nlp
License: UNKNOWN
Platform: UNKNOWN
Requires-Dist: dataclasses (>=0.6)
Requires-Dist: numpy (>=1.18.0)
Requires-Dist: tqdm (>=4.46.0)
Requires-Dist: requests (>=2.20.0)
Requires-Dist: xlrd (>=1.2.0)
